{
  "source": "1 (11).psd",
  "canvas": {
    "w": 2363,
    "h": 3544,
    "ratioWH": 0.6668
  },
  "photoSlots": [
    {
      "x": 0.5036,
      "y": 0.2562,
      "w": 0.4177,
      "h": 0.3781,
      "ratioWH": 0.737
    },
    {
      "x": 0.0758,
      "y": 0.2562,
      "w": 0.4181,
      "h": 0.3781,
      "ratioWH": 0.737
    }
  ],
  "texts": [
    {
      "x": 0.3462,
      "y": 0.1673,
      "w": 0.3055,
      "h": 0.0178,
      "content": "THANH HIỀN & MINH HIẾU",
      "fontSizeRaw": 12.34,
      "font": "'Gilroy-Regular'",
      "fontSizeFrac": 0.01785
    },
    {
      "x": -0.0838,
      "y": 0.7455,
      "w": 1.2344,
      "h": 0.1084,
      "content": "a world filled with endless joy and love",
      "fontSizeRaw": 53.57,
      "font": "'MTD-Royal-Touch'",
      "color": "#cd8381",
      "fontSizeFrac": 0.05654
    },
    {
      "x": 0.2154,
      "y": 0.7125,
      "w": 0.5755,
      "h": 0.1919,
      "content": "Love is not just a feeling; it’s a choice you make every day. It’s about supporting each other through thick and thin, celebrating each other's victories, and finding joy in the smallest moments together.Marriage is a partnership where two people stand side by side, facing the world togetherIt’s about building a life filled with love, laughter, and countless memories that will last a lifetime. In you, I’ve found not just a partner, \rbut a true friend. Someone who understands \rme like no one else, knows my flaws loves me anyway. Together, we create an unbreakable bond.\rHappiness in life comes from sharing it with \rsomeone you love. It’s about finding that \rone person who makes every day brighter, who turns ordinary moments into extraordinary memories.",
      "fontSizeRaw": 15.0,
      "font": "'ScotchDisplayComp-Lt'",
      "fontSizeFrac": 0.01583
    },
    {
      "x": 0.1756,
      "y": 0.0553,
      "w": 0.6483,
      "h": 0.0683,
      "content": "Together we create \ra world filled with endless joy and love.",
      "fontSizeRaw": 12.34,
      "font": "'Gilroy-Regular'",
      "fontSizeFrac": 0.01518
    }
  ]
}